{
  "version": "1.0",
  "timestamp": "2025-12-25T21:58:36.993858",
  "player": {
    "name": "Hero",
    "x": 19,
    "y": 10,
    "stats": {
      "max_health": 110,
      "current_health": 72,
      "max_stamina": 100,
      "current_stamina": 100,
      "strength": 10,
      "magic_power": 20
    },
    "level": 2,
    "experience": 178,
    "inventory": {
      "max_essence": 125.0
    }
  },
  "inventory": {
    "objects": [
      {
        "name": "blade",
        "type": "tools",
        "material": "wood",
        "size": "medium",
        "weight": 0.8,
        "definition": "the flat part of a tool or weapon that (usually) has a cutting edge",
        "source": "wordnet",
        "synset": "blade.n.09",
        "index": 1
      },
      {
        "name": "croquette",
        "type": "food",
        "material": "organic",
        "size": "medium",
        "weight": 0.15,
        "definition": "minced cooked meats (or vegetables) in thick white sauce; breaded and deep-fried",
        "source": "wordnet",
        "synset": "croquette.n.01",
        "index": 2
      },
      {
        "name": "trench knife",
        "type": "weapons",
        "material": "wood",
        "size": "small",
        "weight": 0.8,
        "definition": "a knife with a double-edged blade for hand-to-hand fighting",
        "source": "wordnet",
        "synset": "trench_knife.n.01",
        "ranged": false,
        "damage_bonus": 3,
        "index": 3
      },
      {
        "name": "longbow",
        "type": "weapons",
        "material": "wood",
        "size": "medium",
        "weight": 1.8,
        "definition": "a powerful wooden bow drawn by hand; usually 5-6 feet long; used in medieval England",
        "source": "wordnet",
        "synset": "longbow.n.01",
        "ranged": true,
        "damage_bonus": 6,
        "range": 7,
        "index": 4
      },
      {
        "name": "pyrope",
        "type": "gems",
        "material": "stone",
        "size": "medium",
        "weight": 0.02,
        "definition": "a deep red garnet used as a gemstone",
        "source": "wordnet",
        "synset": "pyrope.n.01",
        "index": 5
      },
      {
        "name": "buckwheat",
        "type": "food",
        "material": "organic",
        "size": "medium",
        "weight": 0.5,
        "definition": "grain ground into flour",
        "source": "wordnet",
        "synset": "buckwheat.n.02",
        "index": 6
      },
      {
        "name": "pitchfork",
        "type": "tools",
        "material": "wood",
        "size": "medium",
        "weight": 1.8,
        "definition": "a long-handled hand tool with sharp widely spaced prongs for lifting and pitching hay",
        "source": "wordnet",
        "synset": "pitchfork.n.01",
        "index": 7
      },
      {
        "name": "Medium Flask of Aqua Ignis",
        "type": "solvent",
        "is_solvent": true,
        "solvent_type": "aqua_ignis",
        "vial_size": "medium",
        "quantity": 50,
        "max_quantity": 50,
        "description": "Boiling alchemical water (50ml)",
        "weight": 0.8,
        "index": 8
      },
      {
        "name": "abrader",
        "type": "tools",
        "material": "wood",
        "size": "medium",
        "weight": 1.2,
        "definition": "a tool or machine used for wearing down or smoothing or polishing",
        "source": "wordnet",
        "synset": "abrader.n.01",
        "index": 9
      },
      {
        "name": "aquamarine",
        "type": "gems",
        "material": "wood",
        "size": "medium",
        "weight": 0.05,
        "definition": "a transparent variety of beryl that is blue green in color",
        "source": "wordnet",
        "synset": "aquamarine.n.01",
        "index": 10
      },
      {
        "name": "Medium Flask of Ite Aether",
        "type": "coagulant",
        "is_coagulant": true,
        "coagulant_type": "ite_aether",
        "vial_size": "medium",
        "quantity": 50,
        "max_quantity": 50,
        "description": "Wispy ethereal mist (50ml)",
        "weight": 0.8,
        "index": 11
      },
      {
        "name": "set gun",
        "type": "weapons",
        "material": "wood",
        "size": "medium",
        "weight": 1.2,
        "definition": "a gun that is set to fire on any intruder that comes in contact with the wire that sets it off",
        "source": "wordnet",
        "synset": "set_gun.n.01",
        "ranged": true,
        "damage_bonus": 8,
        "range": 7,
        "index": 12
      },
      {
        "name": "Tiny Vial of Ite Ignis",
        "type": "coagulant",
        "is_coagulant": true,
        "coagulant_type": "ite_ignis",
        "vial_size": "tiny",
        "quantity": 10,
        "max_quantity": 10,
        "description": "Ite powder (10ml)",
        "weight": 0.2,
        "index": 13
      },
      {
        "name": "food cache",
        "type": "food",
        "material": "organic",
        "size": "medium",
        "weight": 5.0,
        "definition": "food in a secure or hidden storage place",
        "source": "wordnet",
        "synset": "food_cache.n.01",
        "index": 14
      },
      {
        "name": "blit",
        "type": "food",
        "weight": 0.1,
        "essence": {
          "earth": 53,
          "water": 47,
          "fire": 12,
          "air": 8
        },
        "index": 15
      },
      {
        "name": "blit",
        "type": "food",
        "weight": 0.1,
        "essence": {
          "earth": 53,
          "water": 47,
          "fire": 12,
          "air": 8
        },
        "index": 16
      },
      {
        "name": "blit",
        "type": "food",
        "weight": 0.1,
        "essence": {
          "earth": 53,
          "water": 47,
          "fire": 12,
          "air": 8
        },
        "index": 17
      },
      {
        "name": "blit",
        "type": "food",
        "weight": 0.1,
        "essence": {
          "earth": 53,
          "water": 47,
          "fire": 12,
          "air": 8
        },
        "index": 18
      },
      {
        "name": "Small Vial of Oleum Terra",
        "type": "solvent",
        "is_solvent": true,
        "solvent_type": "oleum_terra",
        "vial_size": "small",
        "quantity": 25,
        "max_quantity": 25,
        "description": "Thick mineral oil (25ml)",
        "weight": 0.4,
        "index": 19
      }
    ],
    "essences": {
      "fire": 100.0,
      "water": 100.0,
      "earth": 100.0,
      "air": 100.0
    },
    "grimoire": [
      "heal.v.01",
      "fireball.n.01"
    ]
  },
  "spell_book": {
    "blade.n.09": {
      "name": "blade",
      "synset": "blade.n.09",
      "definition": "the flat part of a tool or weapon that (usually) has a cutting edge",
      "composition": {
        "fire": 15,
        "water": 15,
        "earth": 15,
        "air": 15
      }
    },
    "croquette.n.01": {
      "name": "croquette",
      "synset": "croquette.n.01",
      "definition": "minced cooked meats (or vegetables) in thick white sauce; breaded and deep-fried",
      "composition": {
        "fire": 10,
        "water": 40,
        "earth": 20,
        "air": 5
      }
    },
    "trench_knife.n.01": {
      "name": "trench knife",
      "synset": "trench_knife.n.01",
      "definition": "a knife with a double-edged blade for hand-to-hand fighting",
      "composition": {
        "fire": 15,
        "water": 15,
        "earth": 15,
        "air": 15
      }
    },
    "longbow.n.01": {
      "name": "longbow",
      "synset": "longbow.n.01",
      "definition": "a powerful wooden bow drawn by hand; usually 5-6 feet long; used in medieval England",
      "composition": {
        "fire": 15,
        "water": 15,
        "earth": 15,
        "air": 15
      }
    },
    "pyrope.n.01": {
      "name": "pyrope",
      "synset": "pyrope.n.01",
      "definition": "a deep red garnet used as a gemstone",
      "composition": {
        "fire": 15,
        "water": 15,
        "earth": 15,
        "air": 15
      }
    },
    "buckwheat.n.02": {
      "name": "buckwheat",
      "synset": "buckwheat.n.02",
      "definition": "grain ground into flour",
      "composition": {
        "fire": 10,
        "water": 40,
        "earth": 20,
        "air": 5
      }
    },
    "pitchfork.n.01": {
      "name": "pitchfork",
      "synset": "pitchfork.n.01",
      "definition": "a long-handled hand tool with sharp widely spaced prongs for lifting and pitching hay",
      "composition": {
        "fire": 15,
        "water": 15,
        "earth": 15,
        "air": 15
      }
    },
    "abrader.n.01": {
      "name": "abrader",
      "synset": "abrader.n.01",
      "definition": "a tool or machine used for wearing down or smoothing or polishing",
      "composition": {
        "fire": 15,
        "water": 15,
        "earth": 15,
        "air": 15
      }
    }
  },
  "world": {
    "dungeon_seed": 306664,
    "turn": 92,
    "items_on_ground": {
      "(24, 23)": [
        {
          "name": "weeder",
          "type": "tools",
          "material": "wood",
          "size": "medium",
          "weight": 0.8,
          "definition": "a hand tool for removing weeds",
          "source": "wordnet",
          "synset": "weeder.n.02"
        }
      ],
      "(40, 23)": [
        {
          "name": "jade",
          "type": "gems",
          "material": "stone",
          "size": "medium",
          "weight": 0.05,
          "definition": "a semiprecious gemstone that takes a high polish; is usually green but sometimes whitish; consists of jadeite or nephrite",
          "source": "wordnet",
          "synset": "jade.n.01"
        }
      ],
      "(45, 23)": [
        {
          "name": "near beer",
          "type": "food",
          "material": "organic",
          "size": "medium",
          "weight": 0.35,
          "definition": "drink that resembles beer but with less than 1/2 percent alcohol",
          "source": "wordnet",
          "synset": "near_beer.n.01"
        }
      ],
      "(33, 25)": [
        {
          "name": "dog wrench",
          "type": "tools",
          "material": "wood",
          "size": "medium",
          "weight": 0.8,
          "definition": "a wrench with a handle shaped like a crank",
          "source": "wordnet",
          "synset": "dog_wrench.n.01"
        },
        {
          "name": "Small Vial of Aqua Ignis",
          "type": "solvent",
          "is_solvent": true,
          "solvent_type": "aqua_ignis",
          "vial_size": "small",
          "quantity": 25,
          "max_quantity": 25,
          "description": "Boiling alchemical water (25ml)",
          "weight": 0.4
        }
      ],
      "(20, 23)": [
        {
          "name": "side dish",
          "type": "food",
          "material": "organic",
          "size": "medium",
          "weight": 0.3,
          "definition": "a dish that is served with, but is subordinate to, a main course",
          "source": "wordnet",
          "synset": "side_dish.n.01"
        }
      ],
      "(43, 22)": [
        {
          "name": "edger",
          "type": "tools",
          "material": "wood",
          "size": "medium",
          "weight": 1.2,
          "definition": "garden tool for cutting grass around the edges of a yard",
          "source": "wordnet",
          "synset": "edger.n.02"
        }
      ],
      "(29, 14)": [
        {
          "name": "flamethrower",
          "type": "weapons",
          "material": "wood",
          "size": "medium",
          "weight": 3.2,
          "definition": "a weapon that squirts ignited fuel for several yards",
          "source": "wordnet",
          "synset": "flamethrower.n.01",
          "ranged": false,
          "damage_bonus": 4
        }
      ],
      "(52, 18)": [
        {
          "name": "black opal",
          "type": "gems",
          "material": "wood",
          "size": "medium",
          "weight": 0.05,
          "definition": "a dark colored opal with internal reflections of green or red",
          "source": "wordnet",
          "synset": "black_opal.n.01"
        }
      ],
      "(37, 12)": [
        {
          "name": "fast food",
          "type": "food",
          "material": "organic",
          "size": "medium",
          "weight": 0.3,
          "definition": "inexpensive food (hamburgers or chicken or milkshakes) prepared and served quickly",
          "source": "wordnet",
          "synset": "fast_food.n.01"
        }
      ],
      "(4, 18)": [
        {
          "name": "aquamarine",
          "type": "gems",
          "material": "wood",
          "size": "medium",
          "weight": 0.05,
          "definition": "a transparent variety of beryl that is blue green in color",
          "source": "wordnet",
          "synset": "aquamarine.n.01"
        }
      ],
      "(25, 19)": [
        {
          "name": "orange juice",
          "type": "food",
          "material": "organic",
          "size": "medium",
          "weight": 0.33,
          "definition": "bottled or freshly squeezed juice of oranges",
          "source": "wordnet",
          "synset": "orange_juice.n.01"
        }
      ],
      "(38, 21)": [
        {
          "name": "shotgun",
          "type": "weapons",
          "material": "wood",
          "size": "medium",
          "weight": 3.2,
          "definition": "firearm that is a double-barreled smoothbore shoulder weapon for firing shot at short ranges",
          "source": "wordnet",
          "synset": "shotgun.n.01",
          "ranged": true,
          "damage_bonus": 5,
          "range": 4
        }
      ],
      "(36, 6)": [
        {
          "name": "sard",
          "type": "gems",
          "material": "wood",
          "size": "medium",
          "weight": 0.8,
          "definition": "a deep orange-red variety of chalcedony",
          "source": "wordnet",
          "synset": "sard.n.01"
        }
      ],
      "(38, 11)": [
        {
          "name": "brilliant pebble",
          "type": "weapons",
          "material": "wood",
          "size": "tiny",
          "weight": 0.5,
          "definition": "a code name for a small computerized heat-seeking missile that was supposed to intercept and destroy enemy missiles",
          "source": "wordnet",
          "synset": "brilliant_pebble.n.01",
          "ranged": true,
          "damage_bonus": 8,
          "range": 5
        }
      ],
      "(32, 20)": [
        {
          "name": "barbecued wing",
          "type": "food",
          "material": "organic",
          "size": "medium",
          "weight": 0.3,
          "definition": "chicken wings cooked in barbecue sauce",
          "source": "wordnet",
          "synset": "barbecued_wing.n.01"
        }
      ],
      "(8, 21)": [
        {
          "name": "spiral ratchet screwdriver",
          "type": "tools",
          "material": "wood",
          "size": "medium",
          "weight": 0.8,
          "definition": "a screwdriver with a ratchet (so the blade turns in only one direction) and a spiral in the handle (so the blade rotates) with downward pressure on the handle",
          "source": "wordnet",
          "synset": "spiral_ratchet_screwdriver.n.01"
        }
      ],
      "(53, 11)": [
        {
          "name": "andradite",
          "type": "gems",
          "material": "stone",
          "size": "medium",
          "weight": 0.02,
          "definition": "a garnet consisting of calcium iron silicate and having any color ranging from yellow and green to brown and black; used as gemstone",
          "source": "wordnet",
          "synset": "andradite.n.01"
        }
      ],
      "(7, 23)": [
        {
          "name": "Medium Flask of Oleum Terra",
          "type": "solvent",
          "is_solvent": true,
          "solvent_type": "oleum_terra",
          "vial_size": "medium",
          "quantity": 50,
          "max_quantity": 50,
          "description": "Thick mineral oil (50ml)",
          "weight": 0.8
        }
      ],
      "(50, 25)": [
        {
          "name": "Tiny Vial of Aqua Ignis",
          "type": "solvent",
          "is_solvent": true,
          "solvent_type": "aqua_ignis",
          "vial_size": "tiny",
          "quantity": 10,
          "max_quantity": 10,
          "description": "Boiling alchemical water (10ml)",
          "weight": 0.2
        }
      ],
      "(53, 9)": [
        {
          "name": "Tiny Vial of Oleum Terra",
          "type": "solvent",
          "is_solvent": true,
          "solvent_type": "oleum_terra",
          "vial_size": "tiny",
          "quantity": 10,
          "max_quantity": 10,
          "description": "Thick mineral oil (10ml)",
          "weight": 0.2
        }
      ],
      "(56, 9)": [
        {
          "name": "Grand Bottle of Alkahest",
          "type": "solvent",
          "is_solvent": true,
          "solvent_type": "alkahest",
          "vial_size": "grand",
          "quantity": 200,
          "max_quantity": 200,
          "description": "Universal solvent (200ml)",
          "weight": 3.0
        }
      ],
      "(8, 22)": [
        {
          "name": "Tiny Vial of Oleum Terra",
          "type": "solvent",
          "is_solvent": true,
          "solvent_type": "oleum_terra",
          "vial_size": "tiny",
          "quantity": 10,
          "max_quantity": 10,
          "description": "Thick mineral oil (10ml)",
          "weight": 0.2
        }
      ],
      "(18, 25)": [
        {
          "name": "Tiny Vial of Alkahest",
          "type": "solvent",
          "is_solvent": true,
          "solvent_type": "alkahest",
          "vial_size": "tiny",
          "quantity": 10,
          "max_quantity": 10,
          "description": "Universal solvent (10ml)",
          "weight": 0.2
        }
      ],
      "(40, 25)": [
        {
          "name": "Large Flask of Aqua Ignis",
          "type": "solvent",
          "is_solvent": true,
          "solvent_type": "aqua_ignis",
          "vial_size": "large",
          "quantity": 100,
          "max_quantity": 100,
          "description": "Boiling alchemical water (100ml)",
          "weight": 1.5
        }
      ],
      "(42, 5)": [
        {
          "name": "Small Vial of Alkahest",
          "type": "solvent",
          "is_solvent": true,
          "solvent_type": "alkahest",
          "vial_size": "small",
          "quantity": 25,
          "max_quantity": 25,
          "description": "Universal solvent (25ml)",
          "weight": 0.4
        }
      ],
      "(8, 7)": [
        {
          "name": "Tiny Vial of Aqua Ignis",
          "type": "solvent",
          "is_solvent": true,
          "solvent_type": "aqua_ignis",
          "vial_size": "tiny",
          "quantity": 10,
          "max_quantity": 10,
          "description": "Boiling alchemical water (10ml)",
          "weight": 0.2
        }
      ],
      "(20, 25)": [
        {
          "name": "Small Vial of Oleum Terra",
          "type": "solvent",
          "is_solvent": true,
          "solvent_type": "oleum_terra",
          "vial_size": "small",
          "quantity": 25,
          "max_quantity": 25,
          "description": "Thick mineral oil (25ml)",
          "weight": 0.4
        }
      ],
      "(40, 7)": [
        {
          "name": "Small Vial of Oleum Terra",
          "type": "solvent",
          "is_solvent": true,
          "solvent_type": "oleum_terra",
          "vial_size": "small",
          "quantity": 25,
          "max_quantity": 25,
          "description": "Thick mineral oil (25ml)",
          "weight": 0.4
        }
      ],
      "(15, 13)": [
        {
          "name": "Small Vial of Aqua Ignis",
          "type": "solvent",
          "is_solvent": true,
          "solvent_type": "aqua_ignis",
          "vial_size": "small",
          "quantity": 25,
          "max_quantity": 25,
          "description": "Boiling alchemical water (25ml)",
          "weight": 0.4
        }
      ],
      "(9, 18)": [
        {
          "name": "Tiny Vial of Ite Aqua",
          "type": "coagulant",
          "is_coagulant": true,
          "coagulant_type": "ite_aqua",
          "vial_size": "tiny",
          "quantity": 10,
          "max_quantity": 10,
          "description": "Cool shimmering gel (10ml)",
          "weight": 0.2
        }
      ],
      "(7, 4)": [
        {
          "name": "Tiny Vial of Prima Ite",
          "type": "coagulant",
          "is_coagulant": true,
          "coagulant_type": "prima_ite",
          "vial_size": "tiny",
          "quantity": 10,
          "max_quantity": 10,
          "description": "Universal coagulant (10ml)",
          "weight": 0.2
        }
      ],
      "(15, 21)": [
        {
          "name": "Small Vial of Ite Aether",
          "type": "coagulant",
          "is_coagulant": true,
          "coagulant_type": "ite_aether",
          "vial_size": "small",
          "quantity": 25,
          "max_quantity": 25,
          "description": "Wispy ethereal mist (25ml)",
          "weight": 0.4
        }
      ],
      "(35, 10)": [
        {
          "name": "Large Flask of Ite Terra",
          "type": "coagulant",
          "is_coagulant": true,
          "coagulant_type": "ite_terra",
          "vial_size": "large",
          "quantity": 100,
          "max_quantity": 100,
          "description": "iteiteiteite (100ml)",
          "weight": 1.5
        }
      ],
      "(33, 23)": [
        {
          "name": "Medium Flask of Ite Ignis",
          "type": "coagulant",
          "is_coagulant": true,
          "coagulant_type": "ite_ignis",
          "vial_size": "medium",
          "quantity": 50,
          "max_quantity": 50,
          "description": "Ite powder (50ml)",
          "weight": 0.8
        }
      ],
      "(54, 19)": [
        {
          "name": "Tiny Vial of Prima Ite",
          "type": "coagulant",
          "is_coagulant": true,
          "coagulant_type": "prima_ite",
          "vial_size": "tiny",
          "quantity": 10,
          "max_quantity": 10,
          "description": "Universal coagulant (10ml)",
          "weight": 0.2
        }
      ],
      "(56, 21)": [
        {
          "name": "Small Vial of Prima Ite",
          "type": "coagulant",
          "is_coagulant": true,
          "coagulant_type": "prima_ite",
          "vial_size": "small",
          "quantity": 25,
          "max_quantity": 25,
          "description": "Universal coagulant (25ml)",
          "weight": 0.4
        }
      ],
      "(8, 24)": [
        {
          "name": "Medium Flask of Ite Terra",
          "type": "coagulant",
          "is_coagulant": true,
          "coagulant_type": "ite_terra",
          "vial_size": "medium",
          "quantity": 50,
          "max_quantity": 50,
          "description": "iteiteiteite (50ml)",
          "weight": 0.8
        }
      ]
    }
  },
  "game_state": {
    "running": true,
    "paused": false,
    "show_full_map": false,
    "show_spell_book": false,
    "transmute_mode": false,
    "meditate_mode": false,
    "messages": [
      "Recorded 'abrader' to Spell Book! Essence: F:15, W:15, E:15, A:15",
      "You see 4 items here. (E to pickup)",
      "Picked up blit",
      "Picked up blit",
      "Picked up blit",
      "Picked up blit",
      "You see a Small Vial of Oleum Terra here. (E to pickup)",
      "Picked up Small Vial of Oleum Terra"
    ]
  }
}